planif_neige_client/__init__.py
planif_neige_client/planif_neige_client.py
planif_neige_client-0.1.1.dist-info/DESCRIPTION.rst
planif_neige_client-0.1.1.dist-info/METADATA
planif_neige_client-0.1.1.dist-info/RECORD
planif_neige_client-0.1.1.dist-info/WHEEL
planif_neige_client-0.1.1.dist-info/metadata.json
planif_neige_client-0.1.1.dist-info/top_level.txt
