Metadata-Version: 2.0
Name: planif-neige-client
Version: 0.1.1
Summary: A python client for Montreal's Planif-Neige snow removal API
Home-page: https://github.com/kkr16/planif-neige-client
Author: Karim Roukoz
Author-email: roukoz@gmail.com
License: UNKNOWN
Keywords: montreal,snow removal,neige,deneigement,quebec
Platform: UNKNOWN
Requires-Dist: zeep
